luma/__init__.py
luma/environment.py
luma/exceptions.py
luma/loaders.py
luma/template.py
luma_py-0.1.0rc9.dist-info/METADATA
luma_py-0.1.0rc9.dist-info/WHEEL
luma_py-0.1.0rc9.dist-info/top_level.txt
luma_py-0.1.0rc9.dist-info/RECORD
