Metadata-Version: 2.4
Name: luma-py
Version: 0.1.0rc9
Summary: Lua-powered templating engine with 100% Jinja2 compatibility
Author: Luma Contributors
License: MIT
Project-URL: Homepage, https://github.com/santosr2/luma
Project-URL: Documentation, https://luma.readthedocs.io
Project-URL: Repository, https://github.com/santosr2/luma
Project-URL: Bug Tracker, https://github.com/santosr2/luma/issues
Keywords: template,templating,jinja2,lua,luma
Classifier: Development Status :: 5 - Production/Stable
Classifier: Intended Audience :: Developers
Classifier: License :: OSI Approved :: MIT License
Classifier: Programming Language :: Python :: 3
Classifier: Programming Language :: Python :: 3.9
Classifier: Programming Language :: Python :: 3.10
Classifier: Programming Language :: Python :: 3.11
Classifier: Programming Language :: Python :: 3.12
Classifier: Programming Language :: Python :: 3.13
Classifier: Topic :: Software Development :: Libraries :: Python Modules
Classifier: Topic :: Text Processing :: Markup
Requires-Python: >=3.9
Requires-Dist: lupa>=2.0
Provides-Extra: dev
Requires-Dist: pytest>=7.0; extra == "dev"
Requires-Dist: pytest-cov>=4.0; extra == "dev"
Requires-Dist: black>=23.0; extra == "dev"
Requires-Dist: flake8>=6.0; extra == "dev"
Requires-Dist: mypy>=1.0; extra == "dev"
Provides-Extra: flask
Requires-Dist: flask>=2.0; extra == "flask"
Provides-Extra: django
Requires-Dist: django>=3.2; extra == "django"
